{
  "objectInfo" : {
    "id" : "8eYIAZxDyyEdLeRUTHlCAy",
    "name" : "TF_Invoice_Payment_Netsuite_To_Coupa",
    "type" : "WORKFLOW",
    "metadata" : {
      "modelVersion" : {
        "major" : 0,
        "minor" : 0
      },
      "repoInfo" : {
        "repoHandle" : "000TPB0N000000000009"
      },
      "contextAttributes" : [ {
        "name" : "id",
        "value" : "@1"
      } ],
      "additionalInfo" : {
        "description" : null,
        "contentType" : "JSON",
        "documentState" : "VALID"
      }
    }
  },
  "dataFileExtension" : "zip",
  "objectRefs" : [ {
    "id" : "9aE1I4rT5DMeMA2TOCGZoo",
    "name" : "DSS_Invoice_Payments_04_PUT_File_To_XMLClean",
    "type" : "DSS",
    "metadata" : {
      "modelVersion" : {
        "major" : 0,
        "minor" : 0
      },
      "repoInfo" : {
        "repoHandle" : "000TPB0I000000000075"
      },
      "contextAttributes" : [ {
        "name" : "id",
        "value" : "@1"
      } ],
      "additionalInfo" : {
        "description" : "",
        "contentType" : "JSON",
        "documentState" : "VALID"
      }
    },
    "path" : "/Explore/NetSuite/Coupa"
  }, {
    "id" : "3D5wNKkt9XBgWLBeCyhweD",
    "name" : "DSS_Invoice_Payments_01b_PUT_NSFile_To_File",
    "type" : "DSS",
    "metadata" : {
      "modelVersion" : {
        "major" : 0,
        "minor" : 0
      },
      "repoInfo" : {
        "repoHandle" : "000TPB0I000000000048"
      },
      "contextAttributes" : [ {
        "name" : "id",
        "value" : "@1"
      } ],
      "additionalInfo" : {
        "description" : "",
        "contentType" : "JSON",
        "documentState" : "VALID"
      }
    },
    "path" : "/Explore/NetSuite/Coupa"
  }, {
    "id" : "6gtoFQm3jBGcQXbBiSVtIk",
    "name" : "DSS_Invoice_Payments_01c_PUT_NSFile_To_File_CheckCoupa",
    "type" : "DSS",
    "metadata" : {
      "modelVersion" : {
        "major" : 0,
        "minor" : 0
      },
      "repoInfo" : {
        "repoHandle" : "000TPB0I000000000052"
      },
      "contextAttributes" : [ {
        "name" : "id",
        "value" : "@1"
      } ],
      "additionalInfo" : {
        "description" : "",
        "contentType" : "JSON",
        "documentState" : "VALID"
      }
    },
    "path" : "/Explore/NetSuite/Coupa"
  }, {
    "id" : "79dwZmh2WyQkLoN8fjczq6",
    "name" : "DSS_Invoice_Payments_03_PUT_File_To_XMLUpdate",
    "type" : "DSS",
    "metadata" : {
      "modelVersion" : {
        "major" : 0,
        "minor" : 0
      },
      "repoInfo" : {
        "repoHandle" : "000TPB0I00000000004C"
      },
      "contextAttributes" : [ {
        "name" : "id",
        "value" : "@1"
      } ],
      "additionalInfo" : {
        "description" : "",
        "contentType" : "JSON",
        "documentState" : "VALID"
      }
    },
    "path" : "/Explore/NetSuite/Coupa"
  }, {
    "id" : "eADVlZgs7a7h3mG7FRKjSR",
    "name" : "mct_Invoice_Payments_01a_PUT_NS_To_File",
    "type" : "MTT",
    "metadata" : {
      "modelVersion" : {
        "major" : 0,
        "minor" : 0
      },
      "repoInfo" : {
        "repoHandle" : "000TPB0Z00000000001R"
      },
      "contextAttributes" : [ {
        "name" : "id",
        "value" : "@1"
      } ],
      "additionalInfo" : {
        "description" : "",
        "contentType" : "JSON",
        "documentState" : "VALID"
      }
    },
    "path" : "/Explore/NetSuite/Coupa"
  }, {
    "id" : "1QBdfKCCiL8dLByGA61Loe",
    "name" : "DSS_Invoice_Payments_05_PUT_XMLFile_To_Coupa",
    "type" : "DSS",
    "metadata" : {
      "modelVersion" : {
        "major" : 0,
        "minor" : 0
      },
      "repoInfo" : {
        "repoHandle" : "000TPB0I00000000004B"
      },
      "contextAttributes" : [ {
        "name" : "id",
        "value" : "@1"
      } ],
      "additionalInfo" : {
        "description" : "",
        "contentType" : "JSON",
        "documentState" : "VALID"
      }
    },
    "path" : "/Explore/NetSuite/Coupa"
  }, {
    "id" : "a5X5JDsxcoTgPnVieMmOAq",
    "name" : "mct_Invoice_Payments_06_UpdateParamFile",
    "type" : "MTT",
    "metadata" : {
      "modelVersion" : {
        "major" : 0,
        "minor" : 0
      },
      "repoInfo" : {
        "repoHandle" : "000TPB0Z00000000001S"
      },
      "contextAttributes" : [ {
        "name" : "id",
        "value" : "@1"
      } ],
      "additionalInfo" : {
        "description" : "",
        "contentType" : "JSON",
        "documentState" : "VALID"
      }
    },
    "path" : "/Explore/NetSuite/Coupa"
  }, {
    "id" : "5m4BpgPeWMsfSwzUPExGAj",
    "name" : "DSS_Invoice_Payments_02_PUT_File_To_XMLCreate",
    "type" : "DSS",
    "metadata" : {
      "modelVersion" : {
        "major" : 0,
        "minor" : 0
      },
      "repoInfo" : {
        "repoHandle" : "000TPB0I000000000049"
      },
      "contextAttributes" : [ {
        "name" : "id",
        "value" : "@1"
      } ],
      "additionalInfo" : {
        "description" : "",
        "contentType" : "JSON",
        "documentState" : "VALID"
      }
    },
    "path" : "/Explore/NetSuite/Coupa"
  } ]
}